{
  "lines": [
    {
      "type": "wall",
      "x1": 1245.9107461229366,
      "y1": 417.93435812849896,
      "x2": 1755.7708722110012,
      "y2": 417.93435812849896
    },
    {
      "type": "wall",
      "x1": 139.0,
      "y1": 1088.1034,
      "x2": 600.5806,
      "y2": 1088.1034
    },
    {
      "type": "wall",
      "x1": 1380.7143,
      "y1": 1088.1034,
      "x2": 1623.875,
      "y2": 1088.1034
    },
    {
      "type": "wall",
      "x1": 1380.7143,
      "y1": 1472.2416499999997,
      "x2": 1764.9556367795178,
      "y2": 1472.2416499999997
    },
    {
      "type": "wall",
      "x1": 861.5528215982441,
      "y1": 134.5,
      "x2": 1245.9107461229366,
      "y2": 134.5
    },
    {
      "type": "wall",
      "x1": 861.5528215982441,
      "y1": 256.1765,
      "x2": 902.0,
      "y2": 256.1765
    },
    {
      "type": "wall",
      "x1": 1178.0,
      "y1": 256.1765,
      "x2": 1245.9107461229366,
      "y2": 256.1765
    },
    {
      "type": "wall",
      "x1": 583.7791485439393,
      "y1": 355.0,
      "x2": 861.5528215982441,
      "y2": 355.0
    },
    {
      "type": "wall",
      "x1": 356.75999999999993,
      "y1": 541.2902999999999,
      "x2": 856.9231,
      "y2": 541.2902999999999
    },
    {
      "type": "wall",
      "x1": 1254.8125,
      "y1": 541.2902999999999,
      "x2": 1800.593796428571,
      "y2": 541.2902999999999
    },
    {
      "type": "wall",
      "x1": 1800.593796428571,
      "y1": 559.5143,
      "x2": 1890.41665,
      "y2": 559.5143
    },
    {
      "type": "wall",
      "x1": 139.0,
      "y1": 777.25,
      "x2": 513.0,
      "y2": 777.25
    },
    {
      "type": "wall",
      "x1": 755.4,
      "y1": 777.25,
      "x2": 856.9231,
      "y2": 777.25
    },
    {
      "type": "wall",
      "x1": 1254.8125,
      "y1": 777.25,
      "x2": 1407.0,
      "y2": 777.25
    },
    {
      "type": "wall",
      "x1": 1588.0,
      "y1": 777.25,
      "x2": 1800.593796428571,
      "y2": 777.25
    },
    {
      "type": "wall",
      "x1": 1380.7143,
      "y1": 857.0,
      "x2": 1490.88,
      "y2": 857.0
    },
    {
      "type": "wall",
      "x1": 600.5806,
      "y1": 872.7273000000002,
      "x2": 681.5,
      "y2": 872.7273000000002
    },
    {
      "type": "wall",
      "x1": 755.4,
      "y1": 872.7273000000002,
      "x2": 856.9231,
      "y2": 872.7273000000002
    },
    {
      "type": "wall",
      "x1": 1254.8125,
      "y1": 912.9091000000001,
      "x2": 1312.0,
      "y2": 912.9091000000001
    },
    {
      "type": "wall",
      "x1": 1490.88,
      "y1": 912.9091000000001,
      "x2": 1623.875,
      "y2": 912.9091000000001
    },
    {
      "type": "wall",
      "x1": 1704.0,
      "y1": 912.9091000000001,
      "x2": 1800.593796428571,
      "y2": 912.9091000000001
    },
    {
      "type": "wall",
      "x1": 477.1818,
      "y1": 973.0,
      "x2": 600.5806,
      "y2": 973.0
    },
    {
      "type": "wall",
      "x1": 1380.7143,
      "y1": 1000.0833000000001,
      "x2": 1414.0,
      "y2": 1000.0833000000001
    },
    {
      "type": "wall",
      "x1": 600.5806,
      "y1": 1177.3889,
      "x2": 861.5528215982441,
      "y2": 1177.3889
    },
    {
      "type": "wall",
      "x1": 944.0,
      "y1": 1177.3889,
      "x2": 1283.0,
      "y2": 1177.3889
    },
    {
      "type": "wall",
      "x1": 272.0,
      "y1": 1264.6,
      "x2": 356.75999999999993,
      "y2": 1264.6
    },
    {
      "type": "wall",
      "x1": 1800.593796428571,
      "y1": 1299.7083499999999,
      "x2": 1890.41665,
      "y2": 1299.7083499999999
    },
    {
      "type": "wall",
      "x1": 356.75999999999993,
      "y1": 1324.9545,
      "x2": 463.0,
      "y2": 1324.9545
    },
    {
      "type": "wall",
      "x1": 544.6667,
      "y1": 1324.9545,
      "x2": 600.5806,
      "y2": 1324.9545
    },
    {
      "type": "wall",
      "x1": 1380.7143,
      "y1": 1324.9545,
      "x2": 1431.0,
      "y2": 1324.9545
    },
    {
      "type": "wall",
      "x1": 1712.0,
      "y1": 1324.9545,
      "x2": 1800.593796428571,
      "y2": 1324.9545
    },
    {
      "type": "wall",
      "x1": 600.5806,
      "y1": 1351.125,
      "x2": 672.0,
      "y2": 1351.125
    },
    {
      "type": "wall",
      "x1": 742.5,
      "y1": 1351.125,
      "x2": 861.5528215982441,
      "y2": 1351.125
    },
    {
      "type": "wall",
      "x1": 600.5806,
      "y1": 1514.8125,
      "x2": 1148.7329416709947,
      "y2": 1514.8125
    },
    {
      "type": "wall",
      "x1": 1148.7329416709947,
      "y1": 1650.8462,
      "x2": 1380.7143,
      "y2": 1650.8462
    },
    {
      "type": "wall",
      "x1": 600.5806,
      "y1": 1673.0,
      "x2": 861.5528215982441,
      "y2": 1673.0
    },
    {
      "type": "wall",
      "x1": 861.5528215982441,
      "y1": 1812.0714000000005,
      "x2": 892.0,
      "y2": 1812.0714000000005
    },
    {
      "type": "wall",
      "x1": 1113.0,
      "y1": 1812.0714000000005,
      "x2": 1148.7329416709947,
      "y2": 1812.0714000000005
    },
    {
      "type": "wall",
      "x1": 861.5528215982441,
      "y1": 1890.6250000000002,
      "x2": 1148.7329416709947,
      "y2": 1890.6250000000002
    },
    {
      "type": "window",
      "x1": 463.0,
      "y1": 1324.9545,
      "x2": 544.6667,
      "y2": 1324.9545
    },
    {
      "type": "window",
      "x1": 1431.0,
      "y1": 1324.9545,
      "x2": 1712.0,
      "y2": 1324.9545
    },
    {
      "type": "window",
      "x1": 892.0,
      "y1": 1812.0714000000005,
      "x2": 1113.0,
      "y2": 1812.0714000000005
    },
    {
      "type": "window",
      "x1": 600.5806,
      "y1": 541.2902999999999,
      "x2": 755.4,
      "y2": 541.2902999999999
    },
    {
      "type": "window",
      "x1": 1254.8125,
      "y1": 541.2902999999999,
      "x2": 1490.88,
      "y2": 541.2902999999999
    },
    {
      "type": "window",
      "x1": 691.0,
      "y1": 1514.8125,
      "x2": 767.0,
      "y2": 1514.8125
    },
    {
      "type": "window",
      "x1": 1220.6667,
      "y1": 1650.8462,
      "x2": 1380.7143,
      "y2": 1650.8462
    },
    {
      "type": "door",
      "x1": 1414.0,
      "y1": 1000.0833000000001,
      "x2": 1490.88,
      "y2": 1000.0833000000001
    },
    {
      "type": "door",
      "x1": 902.0,
      "y1": 256.1765,
      "x2": 1178.0,
      "y2": 256.1765
    },
    {
      "type": "door",
      "x1": 513.0,
      "y1": 777.25,
      "x2": 600.5806,
      "y2": 777.25
    },
    {
      "type": "door",
      "x1": 1407.0,
      "y1": 777.25,
      "x2": 1588.0,
      "y2": 777.25
    },
    {
      "type": "door",
      "x1": 681.5,
      "y1": 872.7273000000002,
      "x2": 755.4,
      "y2": 872.7273000000002
    },
    {
      "type": "door",
      "x1": 1312.0,
      "y1": 912.9091000000001,
      "x2": 1490.88,
      "y2": 912.9091000000001
    },
    {
      "type": "door",
      "x1": 861.5528215982441,
      "y1": 1177.3889,
      "x2": 944.0,
      "y2": 1177.3889
    },
    {
      "type": "door",
      "x1": 1283.0,
      "y1": 1177.3889,
      "x2": 1380.7143,
      "y2": 1177.3889
    },
    {
      "type": "door",
      "x1": 672.0,
      "y1": 1351.125,
      "x2": 742.5,
      "y2": 1351.125
    },
    {
      "type": "wall",
      "x1": 583.7791485439393,
      "y1": 355.0,
      "x2": 583.7791485439393,
      "y2": 541.2902999999999
    },
    {
      "type": "wall",
      "x1": 1755.7708722110012,
      "y1": 417.93435812849896,
      "x2": 1755.7708722110012,
      "y2": 541.2902999999999
    },
    {
      "type": "wall",
      "x1": 1764.9556367795178,
      "y1": 1324.9545,
      "x2": 1764.9556367795178,
      "y2": 1472.2416499999997
    },
    {
      "type": "wall",
      "x1": 356.75999999999993,
      "y1": 541.2902999999999,
      "x2": 356.75999999999993,
      "y2": 777.25
    },
    {
      "type": "wall",
      "x1": 356.75999999999993,
      "y1": 1088.1034,
      "x2": 356.75999999999993,
      "y2": 1324.9545
    },
    {
      "type": "wall",
      "x1": 139.0,
      "y1": 777.25,
      "x2": 139.0,
      "y2": 1088.1034
    },
    {
      "type": "wall",
      "x1": 197.0625,
      "y1": 777.25,
      "x2": 197.0625,
      "y2": 1088.1034
    },
    {
      "type": "wall",
      "x1": 272.0,
      "y1": 1088.1034,
      "x2": 272.0,
      "y2": 1264.6
    },
    {
      "type": "wall",
      "x1": 477.1818,
      "y1": 777.25,
      "x2": 477.1818,
      "y2": 1000.0833000000001
    },
    {
      "type": "wall",
      "x1": 600.5806,
      "y1": 541.2902999999999,
      "x2": 600.5806,
      "y2": 872.7273000000002
    },
    {
      "type": "wall",
      "x1": 600.5806,
      "y1": 973.0,
      "x2": 600.5806,
      "y2": 1244.0
    },
    {
      "type": "wall",
      "x1": 600.5806,
      "y1": 1324.9545,
      "x2": 600.5806,
      "y2": 1673.0
    },
    {
      "type": "wall",
      "x1": 755.4,
      "y1": 777.25,
      "x2": 755.4,
      "y2": 872.7273000000002
    },
    {
      "type": "wall",
      "x1": 861.5528215982441,
      "y1": 134.5,
      "x2": 861.5528215982441,
      "y2": 355.0
    },
    {
      "type": "wall",
      "x1": 861.5528215982441,
      "y1": 1177.3889,
      "x2": 861.5528215982441,
      "y2": 1890.6250000000002
    },
    {
      "type": "wall",
      "x1": 856.9231,
      "y1": 541.2902999999999,
      "x2": 856.9231,
      "y2": 872.7273000000002
    },
    {
      "type": "wall",
      "x1": 1148.7329416709947,
      "y1": 1177.3889,
      "x2": 1148.7329416709947,
      "y2": 1514.8125
    },
    {
      "type": "wall",
      "x1": 1148.7329416709947,
      "y1": 1650.8462,
      "x2": 1148.7329416709947,
      "y2": 1890.6250000000002
    },
    {
      "type": "wall",
      "x1": 1245.9107461229366,
      "y1": 134.5,
      "x2": 1245.9107461229366,
      "y2": 417.93435812849896
    },
    {
      "type": "wall",
      "x1": 1254.8125,
      "y1": 541.2902999999999,
      "x2": 1254.8125,
      "y2": 912.9091000000001
    },
    {
      "type": "wall",
      "x1": 1380.7143,
      "y1": 857.0,
      "x2": 1380.7143,
      "y2": 912.9091000000001
    },
    {
      "type": "wall",
      "x1": 1380.7143,
      "y1": 1000.0833000000001,
      "x2": 1380.7143,
      "y2": 1088.1034
    },
    {
      "type": "wall",
      "x1": 1380.7143,
      "y1": 1177.3889,
      "x2": 1380.7143,
      "y2": 1553.0
    },
    {
      "type": "wall",
      "x1": 1380.7143,
      "y1": 1615.0,
      "x2": 1380.7143,
      "y2": 1650.8462
    },
    {
      "type": "wall",
      "x1": 1490.88,
      "y1": 541.2902999999999,
      "x2": 1490.88,
      "y2": 912.9091000000001
    },
    {
      "type": "wall",
      "x1": 1490.88,
      "y1": 1000.0833000000001,
      "x2": 1490.88,
      "y2": 1088.1034
    },
    {
      "type": "wall",
      "x1": 1588.0,
      "y1": 777.25,
      "x2": 1588.0,
      "y2": 912.9091000000001
    },
    {
      "type": "wall",
      "x1": 1623.875,
      "y1": 1000.0833000000001,
      "x2": 1623.875,
      "y2": 1088.1034
    },
    {
      "type": "wall",
      "x1": 1800.593796428571,
      "y1": 541.2902999999999,
      "x2": 1800.593796428571,
      "y2": 637.0
    },
    {
      "type": "wall",
      "x1": 1800.593796428571,
      "y1": 744.6667,
      "x2": 1800.593796428571,
      "y2": 1324.9545
    },
    {
      "type": "wall",
      "x1": 1890.41665,
      "y1": 559.5143,
      "x2": 1890.41665,
      "y2": 1299.7083499999999
    },
    {
      "type": "window",
      "x1": 1800.593796428571,
      "y1": 559.5143,
      "x2": 1800.593796428571,
      "y2": 744.6667
    },
    {
      "type": "window",
      "x1": 1800.593796428571,
      "y1": 912.9091000000001,
      "x2": 1800.593796428571,
      "y2": 1053.0
    },
    {
      "type": "window",
      "x1": 1800.593796428571,
      "y1": 1119.0,
      "x2": 1800.593796428571,
      "y2": 1324.9545
    },
    {
      "type": "window",
      "x1": 197.0625,
      "y1": 850.0,
      "x2": 197.0625,
      "y2": 1018.5
    },
    {
      "type": "window",
      "x1": 356.75999999999993,
      "y1": 1088.1034,
      "x2": 356.75999999999993,
      "y2": 1264.6
    },
    {
      "type": "window",
      "x1": 1380.7143,
      "y1": 1553.0,
      "x2": 1380.7143,
      "y2": 1615.0
    },
    {
      "type": "door",
      "x1": 477.1818,
      "y1": 1000.0833000000001,
      "x2": 477.1818,
      "y2": 1088.1034
    },
    {
      "type": "door",
      "x1": 600.5806,
      "y1": 1244.0,
      "x2": 600.5806,
      "y2": 1324.9545
    },
    {
      "type": "door",
      "x1": 1148.7329416709947,
      "y1": 1514.8125,
      "x2": 1148.7329416709947,
      "y2": 1650.8462
    },
    {
      "type": "door",
      "x1": 1380.7143,
      "y1": 1088.1034,
      "x2": 1380.7143,
      "y2": 1177.3889
    },
    {
      "type": "door",
      "x1": 1490.88,
      "y1": 912.9091000000001,
      "x2": 1490.88,
      "y2": 1000.0833000000001
    },
    {
      "type": "door",
      "x1": 1623.875,
      "y1": 912.9091000000001,
      "x2": 1623.875,
      "y2": 1000.0833000000001
    }
  ]
}